axelrod_fortran/__init__.py
axelrod_fortran/player.py
axelrod_fortran/shared_library_manager.py
axelrod_fortran/strategies.py
axelrod_fortran-0.4.8.dist-info/LICENSE
axelrod_fortran-0.4.8.dist-info/METADATA
axelrod_fortran-0.4.8.dist-info/WHEEL
axelrod_fortran-0.4.8.dist-info/top_level.txt
axelrod_fortran-0.4.8.dist-info/RECORD
