Metadata-Version: 2.1
Name: axelrod-fortran
Version: 0.4.8
Summary: Python wrapper for strategies originally written in Fortran
Home-page: https://github.com/axelrod-python/axelrod-fortran
Author: Owen Campbell, Vincent Knight, Marc Harper
Author-email: axelrod-python@googlegroups.com
License: MIT license
Platform: UNKNOWN
Classifier: Intended Audience :: Developers
Classifier: License :: OSI Approved :: MIT License
Classifier: Operating System :: Unix
Classifier: Operating System :: POSIX
Classifier: Programming Language :: Python
Classifier: Programming Language :: Python :: 3.6
Classifier: Programming Language :: Python :: Implementation :: CPython
Classifier: Topic :: Utilities
Requires-Python: >=3.5
Requires-Dist: axelrod (>=4.5.0)
